annotation_converter
tests
