Metadata-Version: 2.1
Name: mohaliyet-annconv
Version: 0.2
Summary: A utility for converting object detection annotations between different formats.
Home-page: https://www.mohaliy.et
Author: Mohammed Aliy
Author-email: mohammed@mohaliy.et
